<?xml version="1.0" encoding="UTF-8" ?>
<container xmlns="http://symfony.com/schema/dic/services"
           xmlns:xsi="http://www.w3.org/2001/XMLSchema-instance"
           xsi:schemaLocation="http://symfony.com/schema/dic/services
        http://symfony.com/schema/dic/services/services-1.0.xsd">

    <parameters>
        <parameter key="flagbit_table_attribute.validator.constraint_guesser.table.class">Flagbit\Bundle\TableAttributeBundle\Validator\ConstraintGuesser\TableGuesser</parameter>
        <parameter key="flagbit_table_attribute.validator.constraint_factory.class">Flagbit\Bundle\TableAttributeBundle\Validator\ConstraintFactory</parameter>
    </parameters>

    <services>
        <service class="Akeneo\Pim\Structure\Component\Validator\Constraints\AttributeTypeForOptionValidator"
                 id="pim_catalog.validator.constraint.attribute_type_for_option">
            <argument type="collection">
                <argument>pim_catalog_simpleselect</argument>
                <argument>pim_catalog_multiselect</argument>
                <argument>flagbit_catalog_table</argument>
            </argument>
            <tag name="validator.constraint_validator" alias="pim_attribute_type_for_option_validator" />
        </service>

        <service id="flagbit_table_attribute.validator.constraint_guesser.table"
                 class="%flagbit_table_attribute.validator.constraint_guesser.table.class%" public="false">
            <argument id="flagbit_table_attribute.validator.constraint_factory" type="service" />
            <tag name="pim_catalog.constraint_guesser.attribute" alias="pim_enrich_attribute_option" />
        </service>

        <service id="flagbit_table_attribute.validator.constraint_factory" class="%flagbit_table_attribute.validator.constraint_factory.class%" />
    </services>
</container>
